{"black clover":170,"black-clover":170,"bleach":366,"code geass: hangyaku no lelouch":50,"code-geass":50,"dr. stone: science future part 3":58,"dr-stone":58,"dragon ball z":291,"dragon-ball-z":291,"dragon ball":153,"dragon-ball":153,"gachiakuta":2,"gintama.: shirogane no tamashii-hen":369,"gintama":369,"inuyasha":193,"jujutsu kaisen: shimetsu kaiyuu - zenpen":47,"jujutsu-kaisen":47,"naruto: shippuuden":220,"naruto":220,"one piece":1155,"one-piece":1155,"rurouni kenshin: meiji kenkaku romantan (2023)":100,"rurouni-kenshin":100,"sword art online":50,"sword-art-online":50,"tokyo ghoul":24,"tokyo-ghoul":24,"toradora!":25,"toradora":25,"vinland saga":48,"vinland-saga":48}